neuralnoise/__init__.py
neuralnoise/cli.py
neuralnoise/extract.py
neuralnoise/models.py
neuralnoise/tts.py
neuralnoise/utils.py
neuralnoise/prompts/content_analyzer.system.xml
neuralnoise/prompts/editor.system.xml
neuralnoise/prompts/manager.system.xml
neuralnoise/prompts/planner.system.xml
neuralnoise/prompts/script_generation.system.xml
neuralnoise/prompts/user_proxy.message.xml
neuralnoise/prompts/user_proxy.system.xml
neuralnoise/studio/__init__.py
neuralnoise/studio/agents.py
neuralnoise/studio/generate.py
neuralnoise/studio/hooks.py
neuralnoise-1.5.0.dist-info/METADATA
neuralnoise-1.5.0.dist-info/WHEEL
neuralnoise-1.5.0.dist-info/entry_points.txt
neuralnoise-1.5.0.dist-info/licenses/LICENSE
neuralnoise-1.5.0.dist-info/RECORD
