Metadata-Version: 2.3
Name: neuralnoise
Version: 1.5.0
Summary: An AI-powered podcast studio that uses multiple AI agents working together.
Author-email: Leonardo Piñeyro <leopiney@gmail.com>
License: MIT License
Keywords: ai,ai audio generation,autogen,generative ai,notebooklm,podcast
Classifier: Development Status :: 4 - Beta
Classifier: Environment :: Console
Classifier: Intended Audience :: Developers
Classifier: License :: OSI Approved :: Apache Software License
Classifier: License :: OSI Approved :: MIT License
Classifier: Operating System :: OS Independent
Classifier: Programming Language :: Python
Classifier: Programming Language :: Python :: 3 :: Only
Classifier: Programming Language :: Python :: 3.10
Classifier: Programming Language :: Python :: 3.11
Classifier: Programming Language :: Python :: 3.12
Classifier: Topic :: Multimedia :: Sound/Audio
Classifier: Topic :: Multimedia :: Sound/Audio :: Speech
Classifier: Topic :: Scientific/Engineering :: Artificial Intelligence
Requires-Python: <3.12,>=3.10
Requires-Dist: ag2>=0.5.2
Requires-Dist: backoff>=2.2.1
Requires-Dist: beautifulsoup4>=4.12.3
Requires-Dist: crawl4ai>=0.3.3
Requires-Dist: elevenlabs>=1.10.0
Requires-Dist: langchain-community>=0.3.3
Requires-Dist: lxml>=5.3.0
Requires-Dist: openai>=1.52.2
Requires-Dist: pydantic>=2.9.2
Requires-Dist: pydub>=0.25.1
Requires-Dist: pymupdf>=1.24.12
Requires-Dist: python-dotenv>=1.0.1
Requires-Dist: requests>=2.32.3
Requires-Dist: tabulate>=0.9.0
Requires-Dist: tqdm>=4.66.5
Requires-Dist: typer>=0.12.5
Requires-Dist: youtube-transcript-api>=0.6.2
Provides-Extra: local
Requires-Dist: docker>=7.1.0; extra == 'local'
Requires-Dist: ollama>=0.4.4; extra == 'local'
Provides-Extra: streamlit
Requires-Dist: streamlit>=1.39.0; extra == 'streamlit'
